dev-md2html/__init__.py
dev-md2html/converter.py
dev-md2html/converter_html.py
dev-md2html/pygments_style.py
dev-md2html/syntax_highlighting.py
md2html/__init__.py
md2html/converter.py
md2html/converter_html.py
md2html/meta.py
md2html/pygments_style.py
md2html/syntax_highlighting.py
md2html-1.3.0.data/scripts/md2html
test/__init__.py
test/test_package.py
md2html-1.3.0.dist-info/LICENSE
md2html-1.3.0.dist-info/METADATA
md2html-1.3.0.dist-info/WHEEL
md2html-1.3.0.dist-info/top_level.txt
md2html-1.3.0.dist-info/RECORD
