Metadata-Version: 2.1
Name: md2html
Version: 1.3.0
Summary: MD to HTML converter
Home-page: https://github.com/chrispyles/markdown-to-html
Author: Chris Pyles
Author-email: cpyles@berkeley.edu
License: BSD-3-Clause
Platform: UNKNOWN
Classifier: Programming Language :: Python :: 3
Classifier: License :: OSI Approved :: BSD License
Classifier: Operating System :: OS Independent
